tracee/__init__.py
tracee/extract.py
tracee-0.0.3.dist-info/LICENSE
tracee-0.0.3.dist-info/METADATA
tracee-0.0.3.dist-info/WHEEL
tracee-0.0.3.dist-info/top_level.txt
tracee-0.0.3.dist-info/RECORD
