Metadata-Version: 2.1
Name: tracee
Version: 0.0.3
Summary: UNKNOWN
Home-page: UNKNOWN
Author: Ryou Ohsawa
Author-email: ohsawa@ioa.s.u-tokyo.ac.jp
Maintainer: Ryou Ohsawa
Maintainer-email: ohsawa@ioa.s.u-tokyo.ac.jp
License: MIT
Platform: UNKNOWN
Classifier: Development Status :: 3 - Alpha
Classifier: Environment :: Console
Classifier: Intended Audience :: Science/Research
Classifier: License :: OSI Approved :: MIT License
Classifier: Operating System :: POSIX :: Linux
Classifier: Programming Language :: Python :: 3
Classifier: Programming Language :: Python :: 3.7
Classifier: Topic :: Scientific/Engineering :: Astronomy
Requires-Dist: minimalKNN (>=0.5)
Requires-Dist: fdlsgm (>=0.5.5)
